[  { "@id": "http://www.loc.gov/premis/rdf/v3/inhibitedBy", "@type": [ "http://www.w3.org/2002/07/owl#ObjectProperty" ], "http://www.w3.org/2000/01/rdf-schema#label": [ { "@language": "en",
"@value": "inhibited by" } ], "http://www.w3.org/2000/01/rdf-schema#domain": [ { "@id": "_:b762wwwdOtlocdOtgovpremisrdfv3inhibitedBy" } ], "http://www.w3.org/2000/01/rdf-schema#range": [ { "@id": "http://www.loc.gov/premis/rdf/v3/Inhibitor" } ], "http://www.w3.org/2000/01/rdf-schema#isDefinedBy": [ { "@id": "http://www.loc.gov/premis/rdf/v3/" } ] },  { "@id": "_:b930wwwdOtlocdOtgovpremisrdfv3originalName", "@type": [ "http://www.w3.org/2002/07/owl#Class" ], "http://www.w3.org/2002/07/owl#unionOf": [ { "@list": [{"@id": "http://www.loc.gov/premis/rdf/v3/File"}, {"@id": "http://www.loc.gov/premis/rdf/v3/IntellectualEntity"}, {"@id": "http://www.loc.gov/premis/rdf/v3/Representation"} ] } ] },  { "@id": "http://www.loc.gov/premis/rdf/v3/policy", "@type": [ "http://www.w3.org/2002/07/owl#ObjectProperty" ], "http://www.w3.org/2000/01/rdf-schema#label": [ { "@language": "en",
"@value": "has policy" } ], "http://www.w3.org/2000/01/rdf-schema#domain": [ { "@id": "http://www.loc.gov/premis/rdf/v3/Object" } ], "http://www.w3.org/2000/01/rdf-schema#range": [ { "@id": "http://www.loc.gov/premis/rdf/v3/PreservationPolicy" } ], "http://www.w3.org/2000/01/rdf-schema#seeAlso": [ { "@id": "http://id.loc.gov/vocabulary/preservation/preservationLevelRole" } ], "http://www.w3.org/2000/01/rdf-schema#isDefinedBy": [ { "@id": "http://www.loc.gov/premis/rdf/v3/" } ] },  { "@id": "_:b993wwwdOtlocdOtgovpremisrdfv3size", "@type": [ "http://www.w3.org/2002/07/owl#Class" ], "http://www.w3.org/2002/07/owl#unionOf": [ { "@list": [{"@id": "http://www.loc.gov/premis/rdf/v3/Bitstream"}, {"@id": "http://www.loc.gov/premis/rdf/v3/File"} ] } ] },  { "@id": "http://www.loc.gov/premis/rdf/v3/signature", "@type": [ "http://www.w3.org/2002/07/owl#ObjectProperty" ], "http://www.w3.org/2000/01/rdf-schema#label": [ { "@language": "en",
"@value": "has signature" } ], "http://www.w3.org/2000/01/rdf-schema#domain": [ { "@id": "_:b739wwwdOtlocdOtgovpremisrdfv3signature" } ], "http://www.w3.org/2000/01/rdf-schema#range": [ { "@id": "http://www.loc.gov/premis/rdf/v3/Signature" } ], "http://www.w3.org/2000/01/rdf-schema#isDefinedBy": [ { "@id": "http://www.loc.gov/premis/rdf/v3/" } ] },  { "@id": "http://www.loc.gov/premis/rdf/v3/storedAt", "@type": [ "http://www.w3.org/2002/07/owl#ObjectProperty" ], "http://www.w3.org/2000/01/rdf-schema#label": [ { "@language": "en",
"@value": "stored at" } ], "http://www.w3.org/2000/01/rdf-schema#domain": [ { "@id": "_:b809wwwdOtlocdOtgovpremisrdfv3storedAt" } ], "http://www.w3.org/2000/01/rdf-schema#range": [ { "@id": "http://www.loc.gov/premis/rdf/v3/StorageLocation" } ], "http://www.w3.org/2000/01/rdf-schema#isDefinedBy": [ { "@id": "http://www.loc.gov/premis/rdf/v3/" } ] },  { "@id": "http://www.loc.gov/premis/rdf/v3/allows", "@type": [ "http://www.w3.org/2002/07/owl#ObjectProperty" ], "http://www.w3.org/2000/01/rdf-schema#label": [ { "@language": "en",
"@value": "allows" } ], "http://www.w3.org/2000/01/rdf-schema#domain": [ { "@id": "http://www.loc.gov/premis/rdf/v3/RightsBasis" } ], "http://www.w3.org/2000/01/rdf-schema#range": [ { "@id": "http://www.loc.gov/premis/rdf/v3/Rule" } ], "http://www.w3.org/2000/01/rdf-schema#isDefinedBy": [ { "@id": "http://www.loc.gov/premis/rdf/v3/" } ] },  { "@id": "http://www.loc.gov/premis/rdf/v3/characteristic", "@type": [ "http://www.w3.org/2002/07/owl#ObjectProperty" ], "http://www.w3.org/2000/01/rdf-schema#label": [ { "@language": "en",
"@value": "has characteristic" } ], "http://www.w3.org/2000/01/rdf-schema#domain": [ { "@id": "http://www.loc.gov/premis/rdf/v3/Dependency" } ], "http://www.w3.org/2000/01/rdf-schema#range": [ { "@id": "http://www.loc.gov/premis/rdf/v3/EnvironmentCharacteristic" } ], "http://www.w3.org/2000/01/rdf-schema#isDefinedBy": [ { "@id": "http://www.loc.gov/premis/rdf/v3/" } ] },  { "@id": "http://www.loc.gov/premis/rdf/v3/Dependency", "@type": [ "http://www.w3.org/2002/07/owl#Class" ], "http://www.w3.org/2000/01/rdf-schema#label": [ { "@language": "en",
"@value": "Dependency" } ], "http://www.w3.org/2000/01/rdf-schema#comment": [ { "@language": "en",
"@value": "Relationship where one Object requires another Object to support its function, delivery, or\r\n      the coherence of its content." } ], "http://www.w3.org/2000/01/rdf-schema#isDefinedBy": [ { "@id": "http://www.loc.gov/premis/rdf/v3/" } ] },  { "@id": "http://www.loc.gov/premis/rdf/v3/Inhibitor", "@type": [ "http://www.w3.org/2002/07/owl#Class", "http://www.w3.org/2002/07/owl#Class" ], "http://www.w3.org/2000/01/rdf-schema#label": [ { "@language": "en",
"@value": "Inhibitor" } ], "http://www.w3.org/2000/01/rdf-schema#comment": [ { "@language": "en",
"@value": "Feature of a Digital Object intended to inhibit access, copying, dissemination, or\r\n      migration. Common Inhibitors are encryption and password protection." } ], "http://www.w3.org/2000/01/rdf-schema#isDefinedBy": [ { "@id": "http://www.loc.gov/premis/rdf/v3/" } ], "http://www.w3.org/2000/01/rdf-schema#seeAlso": [ { "@id": "http://id.loc.gov/vocabulary/preservation/inhibitorType" } ] },  { "@id": "http://www.loc.gov/premis/rdf/v3/IntellectualEntity", "@type": [ "http://www.w3.org/2002/07/owl#Class", "http://www.w3.org/2002/07/owl#Class", "http://www.w3.org/2002/07/owl#Class" ], "http://www.w3.org/2000/01/rdf-schema#label": [ { "@language": "en",
"@value": "Intellectual entity" } ], "http://www.w3.org/2000/01/rdf-schema#comment": [ { "@language": "en",
"@value": " set of content that is considered a single intellectual unit for purposes of management and\r\n      description: for example, a particular book, map, photograph, database, or piece of hardware or\r\n      software. An Intellectual Entity can include other Intellectual Entities; for example, a web site can\r\n      include a web page; a web page can include an image. An Intellectual Entity may have one or more digital\r\n      representations. An Intellectual Entity may also describe an environment, defined as technology\r\n      supporting a digital object in some way (e.g. by rendering or executing it). Environments can consist of\r\n      software, hardware, or a combination of both." } ], "http://www.w3.org/2000/01/rdf-schema#subClassOf": [ { "@id": "http://www.loc.gov/premis/rdf/v3/Object" } ], "http://www.w3.org/2002/07/owl#disjointWith": [ { "@id": "http://www.loc.gov/premis/rdf/v3/Bitstream" }, { "@id": "http://www.loc.gov/premis/rdf/v3/File" }, { "@id": "http://www.loc.gov/premis/rdf/v3/Representation" } ], "http://www.w3.org/2000/01/rdf-schema#isDefinedBy": [ { "@id": "http://www.loc.gov/premis/rdf/v3/" } ], "http://www.w3.org/2000/01/rdf-schema#seeAlso": [ { "@id": "http://id.loc.gov/vocabulary/preservation/environmentFunctionType" } ] },  { "@id": "http://www.loc.gov/premis/rdf/v3/Representation", "@type": [ "http://www.w3.org/2002/07/owl#Class", "http://www.w3.org/2002/07/owl#Class", "http://www.w3.org/2002/07/owl#Class" ], "http://www.w3.org/2000/01/rdf-schema#label": [ { "@language": "en",
"@value": "Representation" } ], "http://www.w3.org/2000/01/rdf-schema#comment": [ { "@language": "en",
"@value": "Digital or physical Object instantiating or embodying an Intellectual Entity. A digital\r\n      representation is the set of stored digital files and structural metadata needed to provide a complete\r\n      and reasonable rendition of the Intellectual Entity. A physical representation is an item such as a\r\n      manuscript, video cassette, or printed document." } ], "http://www.w3.org/2000/01/rdf-schema#subClassOf": [ { "@id": "http://www.loc.gov/premis/rdf/v3/Object" } ], "http://www.w3.org/2002/07/owl#disjointWith": [ { "@id": "http://www.loc.gov/premis/rdf/v3/Bitstream" }, { "@id": "http://www.loc.gov/premis/rdf/v3/File" }, { "@id": "http://www.loc.gov/premis/rdf/v3/IntellectualEntity" } ], "http://www.w3.org/2000/01/rdf-schema#isDefinedBy": [ { "@id": "http://www.loc.gov/premis/rdf/v3/" } ] },  { "@id": "http://www.loc.gov/premis/rdf/v3/Copyright", "@type": [ "http://www.w3.org/2002/07/owl#Class" ], "http://www.w3.org/2000/01/rdf-schema#label": [ { "@language": "en",
"@value": "Copyright" } ], "http://www.w3.org/2000/01/rdf-schema#comment": [ { "@language": "en",
"@value": "Copyright law." } ], "http://www.w3.org/2000/01/rdf-schema#subClassOf": [ { "@id": "http://www.loc.gov/premis/rdf/v3/RightsBasis" } ], "http://www.w3.org/2000/01/rdf-schema#isDefinedBy": [ { "@id": "http://www.loc.gov/premis/rdf/v3/" } ], "http://www.w3.org/2002/07/owl#disjointWith": [ { "@id": "http://www.loc.gov/premis/rdf/v3/InstitutionalPolicy" }, { "@id": "http://www.loc.gov/premis/rdf/v3/License" }, { "@id": "http://www.loc.gov/premis/rdf/v3/Statute" } ], "http://www.w3.org/2000/01/rdf-schema#seeAlso": [ { "@id": "http://id.loc.gov/vocabulary/preservation/copyrightStatus" } ] },  { "@id": "http://www.loc.gov/premis/rdf/v3/License", "@type": [ "http://www.w3.org/2002/07/owl#Class" ], "http://www.w3.org/2000/01/rdf-schema#label": [ { "@language": "en",
"@value": "License" } ], "http://www.w3.org/2000/01/rdf-schema#comment": [ { "@language": "en",
"@value": "A license agreement or other legal document that grants rights." } ], "http://www.w3.org/2000/01/rdf-schema#subClassOf": [ { "@id": "http://www.loc.gov/premis/rdf/v3/RightsBasis" } ], "http://www.w3.org/2002/07/owl#disjointWith": [ { "@id": "http://www.loc.gov/premis/rdf/v3/Copyright" }, { "@id": "http://www.loc.gov/premis/rdf/v3/InstitutionalPolicy" }, { "@id": "http://www.loc.gov/premis/rdf/v3/Statute" } ], "http://www.w3.org/2000/01/rdf-schema#isDefinedBy": [ { "@id": "http://www.loc.gov/premis/rdf/v3/" } ] },  { "@id": "http://www.loc.gov/premis/rdf/v3/Object", "@type": [ "http://www.w3.org/2002/07/owl#Class", "http://www.w3.org/2002/07/owl#Class" ], "http://www.w3.org/2000/01/rdf-schema#label": [ { "@language": "en",
"@value": "Object" } ], "http://www.w3.org/2000/01/rdf-schema#comment": [ { "@language": "en",
"@value": "Discrete unit of information subject to digital preservation. Subclasses of Object are\r\n      Intellectual Entity, Representation, File and Bitstream." } ], "http://www.w3.org/2000/01/rdf-schema#subClassOf": [ { "@id": "http://www.w3.org/ns/prov#Entity" } ], "http://www.w3.org/2000/01/rdf-schema#isDefinedBy": [ { "@id": "http://www.loc.gov/premis/rdf/v3/" } ] },  { "@id": "http://www.loc.gov/premis/rdf/v3/Agent", "@type": [ "http://www.w3.org/2002/07/owl#Class", "http://www.w3.org/2002/07/owl#Class" ], "http://www.w3.org/2000/01/rdf-schema#label": [ { "@language": "en",
"@value": "Agent" } ], "http://www.w3.org/2000/01/rdf-schema#comment": [ { "@language": "en",
"@value": "Actor (human, machine, or software) associated with one or more Event and/or Rights\r\n      statement associated with a digital object." } ], "http://www.w3.org/2000/01/rdf-schema#subClassOf": [ { "@id": "http://www.w3.org/ns/prov#Agent" }, { "@id": "http://xmlns.com/foaf/0.1/Agent" } ], "http://www.w3.org/2000/01/rdf-schema#isDefinedBy": [ { "@id": "http://www.loc.gov/premis/rdf/v3/" } ] },  { "@id": "http://www.loc.gov/premis/rdf/v3/OutcomeStatus", "@type": [ "http://www.w3.org/2002/07/owl#Class" ], "http://www.w3.org/2000/01/rdf-schema#label": [ { "@language": "en",
"@value": "Outcome status" } ], "http://www.w3.org/2000/01/rdf-schema#comment": [ { "@language": "en",
"@value": "Overall result of the Event in terms of success, partial success, or failure." } ], "http://www.w3.org/2000/01/rdf-schema#isDefinedBy": [ { "@id": "http://www.loc.gov/premis/rdf/v3/" } ], "http://www.w3.org/2000/01/rdf-schema#seeAlso": [ { "@id": "http://id.loc.gov/vocabulary/preservation/eventOutcome" } ] },  { "@id": "http://www.loc.gov/premis/rdf/v3/jurisdiction", "@type": [ "http://www.w3.org/2002/07/owl#ObjectProperty" ], "http://www.w3.org/2000/01/rdf-schema#label": [ { "@language": "en",
"@value": "has jurisdiction" } ], "http://www.w3.org/2000/01/rdf-schema#isDefinedBy": [ { "@id": "http://www.loc.gov/premis/rdf/v3/" } ], "http://www.w3.org/2000/01/rdf-schema#domain": [ { "@id": "http://www.loc.gov/premis/rdf/v3/RightsBasis" } ], "http://www.w3.org/2000/01/rdf-schema#range": [ { "@id": "http://www.w3.org/2000/01/rdf-schema#Resource" } ] },  { "@id": "http://www.loc.gov/premis/rdf/v3/validationRules", "@type": [ "http://www.w3.org/2002/07/owl#DatatypeProperty" ], "http://www.w3.org/2000/01/rdf-schema#label": [ { "@language": "en",
"@value": "has validation rules" } ], "http://www.w3.org/2000/01/rdf-schema#domain": [ { "@id": "http://www.loc.gov/premis/rdf/v3/Signature" } ], "http://www.w3.org/2000/01/rdf-schema#range": [ { "@id": "http://www.w3.org/2000/01/rdf-schema#Literal" } ], "http://www.w3.org/2000/01/rdf-schema#subPropertyOf": [ { "@id": "http://www.loc.gov/premis/rdf/v3/note" } ], "http://www.w3.org/2000/01/rdf-schema#isDefinedBy": [ { "@id": "http://www.loc.gov/premis/rdf/v3/" } ] },  { "@id": "http://www.loc.gov/premis/rdf/v3/inhibits", "@type": [ "http://www.w3.org/2002/07/owl#ObjectProperty" ], "http://www.w3.org/2000/01/rdf-schema#label": [ { "@language": "en",
"@value": "inhibits" } ], "http://www.w3.org/2000/01/rdf-schema#domain": [ { "@id": "http://www.loc.gov/premis/rdf/v3/Inhibitor" } ], "http://www.w3.org/2000/01/rdf-schema#range": [ { "@id": "http://www.loc.gov/premis/rdf/v3/Action" } ], "http://www.w3.org/2000/01/rdf-schema#isDefinedBy": [ { "@id": "http://www.loc.gov/premis/rdf/v3/" } ] },  { "@id": "http://www.loc.gov/premis/rdf/v3/act", "@type": [ "http://www.w3.org/2002/07/owl#ObjectProperty" ], "http://www.w3.org/2000/01/rdf-schema#label": [ { "@language": "en",
"@value": "act" } ], "http://www.w3.org/2000/01/rdf-schema#domain": [ { "@id": "http://www.loc.gov/premis/rdf/v3/Rule" } ], "http://www.w3.org/2000/01/rdf-schema#range": [ { "@id": "http://www.loc.gov/premis/rdf/v3/Action" } ], "http://www.w3.org/2000/01/rdf-schema#isDefinedBy": [ { "@id": "http://www.loc.gov/premis/rdf/v3/" } ] },  { "@id": "_:b1046wwwdOtlocdOtgovpremisrdfv3version", "@type": [ "http://www.w3.org/2002/07/owl#Class" ], "http://www.w3.org/2002/07/owl#unionOf": [ { "@list": [{"@id": "http://purl.org/dc/terms/FileFormat"}, {"@id": "http://www.loc.gov/premis/rdf/v3/HardwareAgent"}, {"@id": "http://www.loc.gov/premis/rdf/v3/IntellectualEntity"}, {"@id": "http://www.loc.gov/premis/rdf/v3/SoftwareAgent"} ] } ] },  { "@id": "http://www.loc.gov/premis/rdf/v3/Rule", "@type": [ "http://www.w3.org/2002/07/owl#Class", "http://www.w3.org/2002/07/owl#Class", "http://www.w3.org/2002/07/owl#Class" ], "http://www.w3.org/2000/01/rdf-schema#label": [ { "@language": "en",
"@value": "Rule" } ], "http://www.w3.org/2000/01/rdf-schema#comment": [ { "@language": "en",
"@value": "Statement about the Actions an Agent is permitted to undertake or prohibited from\r\n      undertaking with respect to an Object." } ], "http://www.w3.org/2000/01/rdf-schema#isDefinedBy": [ { "@id": "http://www.loc.gov/premis/rdf/v3/" } ] },  { "@id": "http://www.loc.gov/premis/rdf/v3/rationale", "@type": [ "http://www.w3.org/2002/07/owl#DatatypeProperty" ], "http://www.w3.org/2000/01/rdf-schema#label": [ { "@language": "en",
"@value": "has rationale" } ], "http://www.w3.org/2000/01/rdf-schema#range": [ { "@id": "http://www.w3.org/2000/01/rdf-schema#Literal" } ], "http://www.w3.org/2000/01/rdf-schema#subPropertyOf": [ { "@id": "http://www.loc.gov/premis/rdf/v3/note" } ], "http://www.w3.org/2000/01/rdf-schema#isDefinedBy": [ { "@id": "http://www.loc.gov/premis/rdf/v3/" } ] },  { "@id": "http://www.loc.gov/premis/rdf/v3/SignatureEncoding", "@type": [ "http://www.w3.org/2002/07/owl#Class" ], "http://www.w3.org/2000/01/rdf-schema#label": [ { "@language": "en",
"@value": "Signature encoding" } ], "http://www.w3.org/2000/01/rdf-schema#comment": [ { "@language": "en",
"@value": "Encoding used for the signature value and key information." } ], "http://www.w3.org/2000/01/rdf-schema#isDefinedBy": [ { "@id": "http://www.loc.gov/premis/rdf/v3/" } ], "http://www.w3.org/2000/01/rdf-schema#seeAlso": [ { "@id": "http://id.loc.gov/vocabulary/preservation/signatureEncoding" } ] },  { "@id": "http://www.loc.gov/premis/rdf/v3/terms", "@type": [ "http://www.w3.org/2002/07/owl#DatatypeProperty" ], "http://www.w3.org/2000/01/rdf-schema#label": [ { "@language": "en",
"@value": "has terms" } ], "http://www.w3.org/2000/01/rdf-schema#domain": [ { "@id": "http://www.loc.gov/premis/rdf/v3/RightsBasis" } ], "http://www.w3.org/2000/01/rdf-schema#range": [ { "@id": "http://www.w3.org/2000/01/rdf-schema#Literal" } ], "http://www.w3.org/2000/01/rdf-schema#subPropertyOf": [ { "@id": "http://www.loc.gov/premis/rdf/v3/note" } ], "http://www.w3.org/2000/01/rdf-schema#isDefinedBy": [ { "@id": "http://www.loc.gov/premis/rdf/v3/" } ] },  { "@id": "http://www.loc.gov/premis/rdf/v3/prohibits", "@type": [ "http://www.w3.org/2002/07/owl#ObjectProperty" ], "http://www.w3.org/2000/01/rdf-schema#label": [ { "@language": "en",
"@value": "prohibits" } ], "http://www.w3.org/2000/01/rdf-schema#domain": [ { "@id": "http://www.loc.gov/premis/rdf/v3/RightsBasis" } ], "http://www.w3.org/2000/01/rdf-schema#range": [ { "@id": "http://www.loc.gov/premis/rdf/v3/Rule" } ], "http://www.w3.org/2000/01/rdf-schema#isDefinedBy": [ { "@id": "http://www.loc.gov/premis/rdf/v3/" } ] },  { "@id": "_:b739wwwdOtlocdOtgovpremisrdfv3signature", "@type": [ "http://www.w3.org/2002/07/owl#Class" ], "http://www.w3.org/2002/07/owl#unionOf": [ { "@list": [{"@id": "http://www.loc.gov/premis/rdf/v3/Bitstream"}, {"@id": "http://www.loc.gov/premis/rdf/v3/File"} ] } ] },  { "@id": "http://www.loc.gov/premis/rdf/v3/determinationDate", "@type": [ "http://www.w3.org/2002/07/owl#DatatypeProperty" ], "http://www.w3.org/2000/01/rdf-schema#label": [ { "@language": "en",
"@value": "has determination date" } ], "http://www.w3.org/2000/01/rdf-schema#domain": [ { "@id": "http://www.loc.gov/premis/rdf/v3/RightsStatus" } ], "http://www.w3.org/2000/01/rdf-schema#range": [ { "@id": "http://www.w3.org/2001/XMLSchema#date" } ], "http://www.w3.org/2000/01/rdf-schema#subPropertyOf": [ { "@id": "http://purl.org/dc/terms/date" } ], "http://www.w3.org/2000/01/rdf-schema#isDefinedBy": [ { "@id": "http://www.loc.gov/premis/rdf/v3/" } ] },  { "@id": "http://www.loc.gov/premis/rdf/v3/note", "@type": [ "http://www.w3.org/2002/07/owl#DatatypeProperty" ], "http://www.w3.org/2000/01/rdf-schema#label": [ { "@language": "en",
"@value": "has note" } ], "http://www.w3.org/2000/01/rdf-schema#range": [ { "@id": "http://www.w3.org/2000/01/rdf-schema#Literal" } ], "http://www.w3.org/2000/01/rdf-schema#subPropertyOf": [ { "@id": "http://purl.org/dc/terms/description" } ], "http://www.w3.org/2000/01/rdf-schema#isDefinedBy": [ { "@id": "http://www.loc.gov/premis/rdf/v3/" } ] },  { "@id": "http://www.loc.gov/premis/rdf/v3/size", "@type": [ "http://www.w3.org/2002/07/owl#DatatypeProperty" ], "http://www.w3.org/2000/01/rdf-schema#label": [ { "@language": "en",
"@value": "has size" } ], "http://www.w3.org/2000/01/rdf-schema#domain": [ { "@id": "_:b993wwwdOtlocdOtgovpremisrdfv3size" } ], "http://www.w3.org/2000/01/rdf-schema#range": [ { "@id": "http://www.w3.org/2001/XMLSchema#nonNegativeInteger" } ], "http://www.w3.org/2000/01/rdf-schema#isDefinedBy": [ { "@id": "http://www.loc.gov/premis/rdf/v3/" } ], "http://www.w3.org/2004/02/skos/core#narrowMatch": [ { "@id": "http://www.ebu.ch/metadata/ontologies/ebucore/ebucore#fileSize" } ] },  { "@id": "http://www.loc.gov/premis/rdf/v3/governs", "@type": [ "http://www.w3.org/2002/07/owl#ObjectProperty" ], "http://www.w3.org/2000/01/rdf-schema#label": [ { "@language": "en",
"@value": "governs" } ], "http://www.w3.org/2000/01/rdf-schema#domain": [ { "@id": "http://www.loc.gov/premis/rdf/v3/RightsBasis" } ], "http://www.w3.org/2000/01/rdf-schema#range": [ { "@id": "http://www.loc.gov/premis/rdf/v3/Object" } ], "http://www.w3.org/2000/01/rdf-schema#isDefinedBy": [ { "@id": "http://www.loc.gov/premis/rdf/v3/" } ] },  { "@id": "_:b605wwwdOtlocdOtgovpremisrdfv3fixity", "@type": [ "http://www.w3.org/2002/07/owl#Class" ], "http://www.w3.org/2002/07/owl#unionOf": [ { "@list": [{"@id": "http://www.loc.gov/premis/rdf/v3/Bitstream"}, {"@id": "http://www.loc.gov/premis/rdf/v3/File"} ] } ] },  { "@id": "_:b762wwwdOtlocdOtgovpremisrdfv3inhibitedBy", "@type": [ "http://www.w3.org/2002/07/owl#Class" ], "http://www.w3.org/2002/07/owl#unionOf": [ { "@list": [{"@id": "http://www.loc.gov/premis/rdf/v3/Bitstream"}, {"@id": "http://www.loc.gov/premis/rdf/v3/File"} ] } ] },  { "@id": "http://www.loc.gov/premis/rdf/v3/File", "@type": [ "http://www.w3.org/2002/07/owl#Class", "http://www.w3.org/2002/07/owl#Class", "http://www.w3.org/2002/07/owl#Class", "http://www.w3.org/2002/07/owl#Class", "http://www.w3.org/2002/07/owl#Class", "http://www.w3.org/2002/07/owl#Class", "http://www.w3.org/2002/07/owl#Class" ], "http://www.w3.org/2000/01/rdf-schema#label": [ { "@language": "en",
"@value": "File" } ], "http://www.w3.org/2000/01/rdf-schema#comment": [ { "@language": "en",
"@value": "Named and ordered sequence of bytes that is known to an operating system." } ], "http://www.w3.org/2000/01/rdf-schema#subClassOf": [ { "@id": "http://www.loc.gov/premis/rdf/v3/Object" } ], "http://www.w3.org/2002/07/owl#disjointWith": [ { "@id": "http://www.loc.gov/premis/rdf/v3/Bitstream" }, { "@id": "http://www.loc.gov/premis/rdf/v3/IntellectualEntity" }, { "@id": "http://www.loc.gov/premis/rdf/v3/Representation" } ], "http://www.w3.org/2000/01/rdf-schema#isDefinedBy": [ { "@id": "http://www.loc.gov/premis/rdf/v3/" } ] },  { "@id": "http://www.loc.gov/premis/rdf/v3/Organization", "@type": [ "http://www.w3.org/2002/07/owl#Class" ], "http://www.w3.org/2000/01/rdf-schema#label": [ { "@language": "en",
"@value": "Organization" } ], "http://www.w3.org/2000/01/rdf-schema#subClassOf": [ { "@id": "http://www.loc.gov/premis/rdf/v3/Agent" }, { "@id": "http://xmlns.com/foaf/0.1/Organization" }, { "@id": "http://www.w3.org/ns/prov#Organization" } ], "http://www.w3.org/2002/07/owl#disjointWith": [ { "@id": "http://www.loc.gov/premis/rdf/v3/HardwareAgent" }, { "@id": "http://www.loc.gov/premis/rdf/v3/Person" }, { "@id": "http://www.loc.gov/premis/rdf/v3/SoftwareAgent" } ], "http://www.w3.org/2000/01/rdf-schema#isDefinedBy": [ { "@id": "http://www.loc.gov/premis/rdf/v3/" } ] },  { "@id": "http://www.loc.gov/premis/rdf/v3/basis", "@type": [ "http://www.w3.org/2002/07/owl#ObjectProperty" ], "http://www.w3.org/2000/01/rdf-schema#label": [ { "@language": "en",
"@value": "has basis" } ], "http://www.w3.org/2000/01/rdf-schema#comment": [ { "@language": "en",
"@value": "Links from a RightsStatus to the RightsBasis instance that supports or documents\r\n      it." } ], "http://www.w3.org/2000/01/rdf-schema#domain": [ { "@id": "http://www.loc.gov/premis/rdf/v3/RightsStatus" } ], "http://www.w3.org/2000/01/rdf-schema#range": [ { "@id": "http://www.loc.gov/premis/rdf/v3/RightsBasis" } ], "http://www.w3.org/2000/01/rdf-schema#isDefinedBy": [ { "@id": "http://www.loc.gov/premis/rdf/v3/" } ] },  { "@id": "http://www.loc.gov/premis/rdf/v3/documentation", "@type": [ "http://www.w3.org/2002/07/owl#ObjectProperty" ], "http://www.w3.org/2000/01/rdf-schema#label": [ { "@language": "en",
"@value": "has documentation" } ], "http://www.w3.org/2000/01/rdf-schema#range": [ { "@id": "http://www.w3.org/2000/01/rdf-schema#Resource" } ], "http://www.w3.org/2000/01/rdf-schema#isDefinedBy": [ { "@id": "http://www.loc.gov/premis/rdf/v3/" } ] },  { "@id": "http://www.loc.gov/premis/rdf/v3/rightsStatus", "@type": [ "http://www.w3.org/2002/07/owl#ObjectProperty" ], "http://www.w3.org/2000/01/rdf-schema#label": [ { "@language": "en",
"@value": "has rights status" } ], "http://www.w3.org/2000/01/rdf-schema#subPropertyOf": [ { "@id": "http://purl.org/dc/elements/1.1/rights" } ], "http://www.w3.org/2000/01/rdf-schema#domain": [ { "@id": "http://www.loc.gov/premis/rdf/v3/Object" } ], "http://www.w3.org/2000/01/rdf-schema#range": [ { "@id": "http://www.loc.gov/premis/rdf/v3/RightsStatus" } ], "http://www.w3.org/2000/01/rdf-schema#isDefinedBy": [ { "@id": "http://www.loc.gov/premis/rdf/v3/" } ] },  { "@id": "http://www.loc.gov/premis/rdf/v3/citation", "@type": [ "http://www.w3.org/2002/07/owl#DatatypeProperty" ], "http://www.w3.org/2000/01/rdf-schema#label": [ { "@language": "en",
"@value": "has citation" } ], "http://www.w3.org/2000/01/rdf-schema#domain": [ { "@id": "http://www.loc.gov/premis/rdf/v3/RightsBasis" } ], "http://www.w3.org/2000/01/rdf-schema#range": [ { "@id": "http://www.w3.org/2000/01/rdf-schema#Literal" } ], "http://www.w3.org/2000/01/rdf-schema#isDefinedBy": [ { "@id": "http://www.loc.gov/premis/rdf/v3/" } ] },  { "@id": "http://purl.org/dc/terms/FileFormat", "@type": [ "http://www.w3.org/2002/07/owl#Class" ] },  { "@id": "http://www.loc.gov/premis/rdf/v3/Event", "@type": [ "http://www.w3.org/2002/07/owl#Class" ], "http://www.w3.org/2000/01/rdf-schema#label": [ { "@language": "en",
"@value": "Event" } ], "http://www.w3.org/2000/01/rdf-schema#comment": [ { "@language": "en",
"@value": "Action performed within or outside the repository that affects its capability to preserve Objects over the long term." } ], "http://www.w3.org/2000/01/rdf-schema#subClassOf": [ { "@id": "http://www.w3.org/ns/prov#Activity" } ], "http://www.w3.org/2000/01/rdf-schema#isDefinedBy": [ { "@id": "http://www.loc.gov/premis/rdf/v3/" } ], "http://www.w3.org/2000/01/rdf-schema#seeAlso": [ { "@id": "http://id.loc.gov/vocabulary/preservation/eventType" } ] },  { "@id": "http://www.loc.gov/premis/rdf/v3/restriction", "@type": [ "http://www.w3.org/2002/07/owl#DatatypeProperty" ], "http://www.w3.org/2000/01/rdf-schema#label": [ { "@language": "en",
"@value": "has restriction" } ], "http://www.w3.org/2000/01/rdf-schema#domain": [ { "@id": "http://www.loc.gov/premis/rdf/v3/Rule" } ], "http://www.w3.org/2000/01/rdf-schema#range": [ { "@id": "http://www.w3.org/2000/01/rdf-schema#Literal" } ], "http://www.w3.org/2000/01/rdf-schema#isDefinedBy": [ { "@id": "http://www.loc.gov/premis/rdf/v3/" } ] },  { "@id": "http://www.loc.gov/premis/rdf/v3/originalName", "@type": [ "http://www.w3.org/2002/07/owl#DatatypeProperty" ], "http://www.w3.org/2000/01/rdf-schema#label": [ { "@language": "en",
"@value": "has original name" } ], "http://www.w3.org/2000/01/rdf-schema#domain": [ { "@id": "_:b930wwwdOtlocdOtgovpremisrdfv3originalName" } ], "http://www.w3.org/2000/01/rdf-schema#range": [ { "@id": "http://www.w3.org/2000/01/rdf-schema#Literal" } ], "http://www.w3.org/2000/01/rdf-schema#isDefinedBy": [ { "@id": "http://www.loc.gov/premis/rdf/v3/" } ] },  { "@id": "http://www.loc.gov/premis/rdf/v3/InstitutionalPolicy", "@type": [ "http://www.w3.org/2002/07/owl#Class" ], "http://www.w3.org/2000/01/rdf-schema#label": [ { "@language": "en",
"@value": "Institutional policy" } ], "http://www.w3.org/2000/01/rdf-schema#comment": [ { "@language": "en",
"@value": "A policy decision made by an organization." } ], "http://www.w3.org/2000/01/rdf-schema#subClassOf": [ { "@id": "http://www.loc.gov/premis/rdf/v3/RightsBasis" } ], "http://www.w3.org/2002/07/owl#disjointWith": [ { "@id": "http://www.loc.gov/premis/rdf/v3/Copyright" }, { "@id": "http://www.loc.gov/premis/rdf/v3/License" }, { "@id": "http://www.loc.gov/premis/rdf/v3/Statute" } ], "http://www.w3.org/2000/01/rdf-schema#isDefinedBy": [ { "@id": "http://www.loc.gov/premis/rdf/v3/" } ] },  { "@id": "http://www.loc.gov/premis/rdf/v3/PreservationPolicy", "@type": [ "http://www.w3.org/2002/07/owl#Class" ], "http://www.w3.org/2000/01/rdf-schema#label": [ { "@language": "en",
"@value": "Preservation policy" } ], "http://www.w3.org/2000/01/rdf-schema#comment": [ { "@language": "en",
"@value": "Information indicating the decision or policy on the set of preservation functions to be\r\n      applied to an object and the context in which the decision or policy was made. Note that in addition to\r\n      subclasses declared at presLevType, SignificantProperties is also a subclass of PreservationPolicy.\r\n      Implementers may also wish to create locally-defined subclasses." } ], "http://www.w3.org/2000/01/rdf-schema#subClassOf": [ { "@id": "http://purl.org/dc/terms/Policy" } ], "http://www.w3.org/2000/01/rdf-schema#isDefinedBy": [ { "@id": "http://www.loc.gov/premis/rdf/v3/" } ], "http://www.w3.org/2000/01/rdf-schema#seeAlso": [ { "@id": "http://id.loc.gov/vocabulary/preservation/preservationLevelRole" } ] },  { "@id": "http://www.loc.gov/premis/rdf/v3/Action", "@type": [ "http://www.w3.org/2002/07/owl#Class" ], "http://www.w3.org/2000/01/rdf-schema#label": [ { "@language": "en",
"@value": "Action" } ], "http://www.w3.org/2000/01/rdf-schema#comment": [ { "@language": "en",
"@value": "Operation type to perform on an Object. Effectively performing this action may produce an Event." } ], "http://www.w3.org/2000/01/rdf-schema#isDefinedBy": [ { "@id": "http://www.loc.gov/premis/rdf/v3/" } ], "http://www.w3.org/2000/01/rdf-schema#seeAlso": [ { "@id": "http://id.loc.gov/vocabulary/preservation/actionsGranted" } ] },  { "@id": "http://www.loc.gov/premis/rdf/v3/fixity", "@type": [ "http://www.w3.org/2002/07/owl#ObjectProperty" ], "http://www.w3.org/2000/01/rdf-schema#label": [ { "@language": "en",
"@value": "has fixity" } ], "http://www.w3.org/2000/01/rdf-schema#domain": [ { "@id": "_:b605wwwdOtlocdOtgovpremisrdfv3fixity" } ], "http://www.w3.org/2000/01/rdf-schema#range": [ { "@id": "http://www.loc.gov/premis/rdf/v3/Fixity" } ], "http://www.w3.org/2000/01/rdf-schema#isDefinedBy": [ { "@id": "http://www.loc.gov/premis/rdf/v3/" } ] },  { "@id": "_:b809wwwdOtlocdOtgovpremisrdfv3storedAt", "@type": [ "http://www.w3.org/2002/07/owl#Class" ], "http://www.w3.org/2002/07/owl#unionOf": [ { "@list": [{"@id": "http://www.loc.gov/premis/rdf/v3/Bitstream"}, {"@id": "http://www.loc.gov/premis/rdf/v3/File"}, {"@id": "http://www.loc.gov/premis/rdf/v3/Representation"} ] } ] },  { "@id": "http://www.loc.gov/premis/rdf/v3/Fixity", "@type": [ "http://www.w3.org/2002/07/owl#Class" ], "http://www.w3.org/2000/01/rdf-schema#label": [ { "@language": "en",
"@value": "Fixity" } ], "http://www.w3.org/2000/01/rdf-schema#comment": [ { "@language": "en",
"@value": "Information used to verify whether an object has been altered in an undocumented or\r\n      unauthorized way." } ], "http://www.w3.org/2000/01/rdf-schema#isDefinedBy": [ { "@id": "http://www.loc.gov/premis/rdf/v3/" } ], "http://www.w3.org/2000/01/rdf-schema#seeAlso": [ { "@id": "http://id.loc.gov/vocabulary/preservation/cryptographicHashFunctions" } ] },  { "@id": "http://www.loc.gov/premis/rdf/v3/SoftwareAgent", "@type": [ "http://www.w3.org/2002/07/owl#Class", "http://www.w3.org/2002/07/owl#Class" ], "http://www.w3.org/2000/01/rdf-schema#label": [ { "@language": "en",
"@value": "Software agent" } ], "http://www.w3.org/2000/01/rdf-schema#subClassOf": [ { "@id": "http://www.loc.gov/premis/rdf/v3/Agent" }, { "@id": "http://www.w3.org/ns/prov#SoftwareAgent" } ], "http://www.w3.org/2002/07/owl#disjointWith": [ { "@id": "http://www.loc.gov/premis/rdf/v3/HardwareAgent" }, { "@id": "http://www.loc.gov/premis/rdf/v3/Organization" }, { "@id": "http://www.loc.gov/premis/rdf/v3/Person" } ], "http://www.w3.org/2000/01/rdf-schema#isDefinedBy": [ { "@id": "http://www.loc.gov/premis/rdf/v3/" } ] },  { "@id": "http://www.loc.gov/premis/rdf/v3/startDate", "@type": [ "http://www.w3.org/2002/07/owl#DatatypeProperty" ], "http://www.w3.org/2000/01/rdf-schema#label": [ { "@language": "en",
"@value": "start date" } ], "http://www.w3.org/2000/01/rdf-schema#domain": [ { "@id": "_:b1073wwwdOtlocdOtgovpremisrdfv3startDate" } ], "http://www.w3.org/2000/01/rdf-schema#subPropertyOf": [ { "@id": "http://purl.org/dc/terms/date" } ], "http://www.w3.org/2000/01/rdf-schema#isDefinedBy": [ { "@id": "http://www.loc.gov/premis/rdf/v3/" } ] },  { "@id": "http://www.loc.gov/premis/rdf/v3/identifier", "@type": [ "http://www.w3.org/2002/07/owl#ObjectProperty" ], "http://www.w3.org/2000/01/rdf-schema#label": [ { "@language": "en",
"@value": "has identifier" } ], "http://www.w3.org/2000/01/rdf-schema#range": [ { "@id": "http://www.loc.gov/premis/rdf/v3/Identifier" } ], "http://www.w3.org/2000/01/rdf-schema#isDefinedBy": [ { "@id": "http://www.loc.gov/premis/rdf/v3/" } ] },  { "@id": "http://www.loc.gov/premis/rdf/v3/StorageLocation", "@type": [ "http://www.w3.org/2002/07/owl#Class" ], "http://www.w3.org/2000/01/rdf-schema#label": [ { "@language": "en",
"@value": "Storage location" } ], "http://www.w3.org/2000/01/rdf-schema#comment": [ { "@language": "en",
"@value": "Information needed to retrieve a physical item from its physical storage location or a file\r\n      from the storage system, or to access a bitstream within a file." } ], "http://www.w3.org/2000/01/rdf-schema#isDefinedBy": [ { "@id": "http://www.loc.gov/premis/rdf/v3/" } ], "http://www.w3.org/2000/01/rdf-schema#seeAlso": [ { "@id": "http://id.loc.gov/vocabulary/preservation/contentLocationType" } ] },  { "@id": "http://www.loc.gov/premis/rdf/v3/outcomeNote", "@type": [ "http://www.w3.org/2002/07/owl#DatatypeProperty" ], "http://www.w3.org/2000/01/rdf-schema#label": [ { "@language": "en",
"@value": "has outcome note" } ], "http://www.w3.org/2000/01/rdf-schema#domain": [ { "@id": "http://www.loc.gov/premis/rdf/v3/Event" } ], "http://www.w3.org/2000/01/rdf-schema#range": [ { "@id": "http://www.w3.org/2000/01/rdf-schema#Literal" } ], "http://www.w3.org/2000/01/rdf-schema#subPropertyOf": [ { "@id": "http://www.loc.gov/premis/rdf/v3/note" } ], "http://www.w3.org/2000/01/rdf-schema#isDefinedBy": [ { "@id": "http://www.loc.gov/premis/rdf/v3/" } ] },  { "@id": "_:b1073wwwdOtlocdOtgovpremisrdfv3startDate", "@type": [ "http://www.w3.org/2002/07/owl#Class" ], "http://www.w3.org/2002/07/owl#unionOf": [ { "@list": [{"@id": "http://www.loc.gov/premis/rdf/v3/RightsStatus"}, {"@id": "http://www.loc.gov/premis/rdf/v3/Rule"} ] } ] },  { "@id": "http://www.loc.gov/premis/rdf/v3/RightsBasis", "@type": [ "http://www.w3.org/2002/07/owl#Class" ], "http://www.w3.org/2000/01/rdf-schema#label": [ { "@language": "en",
"@value": "Rights basis" } ], "http://www.w3.org/2000/01/rdf-schema#comment": [ { "@language": "en",
"@value": "Designation of the basis for the right or permission governing the Object." } ], "http://www.w3.org/2000/01/rdf-schema#isDefinedBy": [ { "@id": "http://www.loc.gov/premis/rdf/v3/" } ], "http://www.w3.org/2000/01/rdf-schema#seeAlso": [ { "@id": "http://id.loc.gov/vocabulary/preservation/rightsBasis" } ] },  { "@id": "http://www.loc.gov/premis/rdf/v3/HardwareAgent", "@type": [ "http://www.w3.org/2002/07/owl#Class", "http://www.w3.org/2002/07/owl#Class" ], "http://www.w3.org/2000/01/rdf-schema#label": [ { "@language": "en",
"@value": "Hardware agent" } ], "http://www.w3.org/2000/01/rdf-schema#subClassOf": [ { "@id": "http://www.loc.gov/premis/rdf/v3/Agent" } ], "http://www.w3.org/2002/07/owl#sameAs": [ { "@id": "http://id.loc.gov/vocabulary/preservation/agentType/har" } ], "http://www.w3.org/2002/07/owl#disjointWith": [ { "@id": "http://www.loc.gov/premis/rdf/v3/Organization" }, { "@id": "http://www.loc.gov/premis/rdf/v3/Person" }, { "@id": "http://www.loc.gov/premis/rdf/v3/SoftwareAgent" } ], "http://www.w3.org/2000/01/rdf-schema#isDefinedBy": [ { "@id": "http://www.loc.gov/premis/rdf/v3/" } ] },  { "@id": "http://www.loc.gov/premis/rdf/v3/Person", "@type": [ "http://www.w3.org/2002/07/owl#Class" ], "http://www.w3.org/2000/01/rdf-schema#label": [ { "@language": "en",
"@value": "Person" } ], "http://www.w3.org/2000/01/rdf-schema#subClassOf": [ { "@id": "http://www.loc.gov/premis/rdf/v3/Agent" }, { "@id": "http://www.w3.org/ns/prov#Person" }, { "@id": "http://xmlns.com/foaf/0.1/Person" } ], "http://www.w3.org/2002/07/owl#disjointWith": [ { "@id": "http://www.loc.gov/premis/rdf/v3/HardwareAgent" }, { "@id": "http://www.loc.gov/premis/rdf/v3/Organization" }, { "@id": "http://www.loc.gov/premis/rdf/v3/SoftwareAgent" } ], "http://www.w3.org/2000/01/rdf-schema#isDefinedBy": [ { "@id": "http://www.loc.gov/premis/rdf/v3/" } ] },  { "@id": "http://www.loc.gov/premis/rdf/v3/", "@type": [ "http://www.w3.org/2002/07/owl#Ontology" ], "http://www.w3.org/2000/01/rdf-schema#label": [ { "@language": "en",
"@value": "PREMIS 3 Ontology" } ], "http://www.w3.org/2000/01/rdf-schema#comment": [ { "@language": "en",
"@value": "Ontology for PREMIS 3, the international standard\r\n      for metadata to support the preservation of digital objects and ensure their\r\n      long-term usability." } ], "http://purl.org/dc/terms/modified": [ { "@type": "http://www.w3.org/2001/XMLSchema#date",
"@value": "2018-10-12" } ], "http://www.w3.org/2002/07/owl#versionInfo": [ { "@type": "http://www.w3.org/2001/XMLSchema#string",
"@value": "2018/10/12" } ], "http://www.w3.org/2002/07/owl#versionIRI": [ { "@id": "http://www.loc.gov/premis/rdf/v3/2018/10/12/" } ], "http://www.w3.org/2000/01/rdf-schema#seeAlso": [ { "@id": "http://www.loc.gov/standards/premis/" }, { "@id": "https://github.com/PREMIS-OWL-Revision-Team/revise-premis-owl/" } ], "http://www.w3.org/2002/07/owl#imports": [ { "@id": "http://www.w3.org/ns/prov-o-20130430" } ] },  { "@id": "http://www.loc.gov/premis/rdf/v3/Signature", "@type": [ "http://www.w3.org/2002/07/owl#Class", "http://www.w3.org/2002/07/owl#Class" ], "http://www.w3.org/2000/01/rdf-schema#label": [ { "@language": "en",
"@value": "Signature" } ], "http://www.w3.org/2000/01/rdf-schema#comment": [ { "@language": "en",
"@value": "Mathematical technique used to validate the authenticity and integrity of a message,\r\n      software or digital document." } ], "http://www.w3.org/2000/01/rdf-schema#isDefinedBy": [ { "@id": "http://www.loc.gov/premis/rdf/v3/" } ], "http://www.w3.org/2000/01/rdf-schema#seeAlso": [ { "@id": "http://id.loc.gov/vocabulary/preservation/signatureMethod" } ] },  { "@id": "http://www.loc.gov/premis/rdf/v3/StorageMedium", "@type": [ "http://www.w3.org/2002/07/owl#Class" ], "http://www.w3.org/2000/01/rdf-schema#label": [ { "@language": "en",
"@value": "Storage medium" } ], "http://www.w3.org/2000/01/rdf-schema#comment": [ { "@language": "en",
"@value": "The physical medium on which the Object is stored (e.g., magnetic tape, hard disk, CD-ROM,\r\n      DVD)." } ], "http://www.w3.org/2000/01/rdf-schema#isDefinedBy": [ { "@id": "http://www.loc.gov/premis/rdf/v3/" } ], "http://www.w3.org/2000/01/rdf-schema#seeAlso": [ { "@id": "http://id.loc.gov/vocabulary/preservation/storageMedium" } ] },  { "@id": "http://www.loc.gov/premis/rdf/v3/endDate", "@type": [ "http://www.w3.org/2002/07/owl#DatatypeProperty" ], "http://www.w3.org/2000/01/rdf-schema#label": [ { "@language": "en",
"@value": "end date" } ], "http://www.w3.org/2000/01/rdf-schema#domain": [ { "@id": "_:b834wwwdOtlocdOtgovpremisrdfv3endDate" } ], "http://www.w3.org/2000/01/rdf-schema#subPropertyOf": [ { "@id": "http://purl.org/dc/terms/date" } ], "http://www.w3.org/2000/01/rdf-schema#isDefinedBy": [ { "@id": "http://www.loc.gov/premis/rdf/v3/" } ] },  { "@id": "http://www.loc.gov/premis/rdf/v3/Bitstream", "@type": [ "http://www.w3.org/2002/07/owl#Class", "http://www.w3.org/2002/07/owl#Class", "http://www.w3.org/2002/07/owl#Class", "http://www.w3.org/2002/07/owl#Class", "http://www.w3.org/2002/07/owl#Class", "http://www.w3.org/2002/07/owl#Class" ], "http://www.w3.org/2000/01/rdf-schema#label": [ { "@language": "en",
"@value": "Bitstream" } ], "http://www.w3.org/2000/01/rdf-schema#comment": [ { "@language": "en",
"@value": "Contiguous or non-contiguous data within a file that has meaningful properties for\r\n      preservation purposes." } ], "http://www.w3.org/2000/01/rdf-schema#subClassOf": [ { "@id": "http://www.loc.gov/premis/rdf/v3/Object" } ], "http://www.w3.org/2002/07/owl#disjointWith": [ { "@id": "http://www.loc.gov/premis/rdf/v3/File" }, { "@id": "http://www.loc.gov/premis/rdf/v3/IntellectualEntity" }, { "@id": "http://www.loc.gov/premis/rdf/v3/Representation" } ], "http://www.w3.org/2000/01/rdf-schema#isDefinedBy": [ { "@id": "http://www.loc.gov/premis/rdf/v3/" } ] },  { "@id": "http://www.loc.gov/premis/rdf/v3/dependency", "@type": [ "http://www.w3.org/2002/07/owl#ObjectProperty" ], "http://www.w3.org/2000/01/rdf-schema#label": [ { "@language": "en",
"@value": "has dependency" } ], "http://www.w3.org/2000/01/rdf-schema#domain": [ { "@id": "http://www.loc.gov/premis/rdf/v3/Object" } ], "http://www.w3.org/2000/01/rdf-schema#range": [ { "@id": "http://www.loc.gov/premis/rdf/v3/Dependency" } ], "http://www.w3.org/2000/01/rdf-schema#isDefinedBy": [ { "@id": "http://www.loc.gov/premis/rdf/v3/" } ] },  { "@id": "http://www.loc.gov/premis/rdf/v3/encoding", "@type": [ "http://www.w3.org/2002/07/owl#ObjectProperty" ], "http://www.w3.org/2000/01/rdf-schema#label": [ { "@language": "en",
"@value": "has encoding" } ], "http://www.w3.org/2000/01/rdf-schema#domain": [ { "@id": "http://www.loc.gov/premis/rdf/v3/Signature" } ], "http://www.w3.org/2000/01/rdf-schema#range": [ { "@id": "http://www.loc.gov/premis/rdf/v3/SignatureEncoding" } ], "http://www.w3.org/2000/01/rdf-schema#isDefinedBy": [ { "@id": "http://www.loc.gov/premis/rdf/v3/" } ] },  { "@id": "_:b895wwwdOtlocdOtgovpremisrdfv3key", "@type": [ "http://www.w3.org/2002/07/owl#Class" ], "http://www.w3.org/2002/07/owl#unionOf": [ { "@list": [{"@id": "http://www.loc.gov/premis/rdf/v3/Inhibitor"}, {"@id": "http://www.loc.gov/premis/rdf/v3/Signature"} ] } ] },  { "@id": "http://www.loc.gov/premis/rdf/v3/Statute", "@type": [ "http://www.w3.org/2002/07/owl#Class" ], "http://www.w3.org/2000/01/rdf-schema#label": [ { "@language": "en",
"@value": "Statute" } ], "http://www.w3.org/2000/01/rdf-schema#comment": [ { "@language": "en",
"@value": "A law that grants or revokes rights, such as laws governing privacy or orphan\r\n      works." } ], "http://www.w3.org/2000/01/rdf-schema#subClassOf": [ { "@id": "http://www.loc.gov/premis/rdf/v3/RightsBasis" } ], "http://www.w3.org/2002/07/owl#disjointWith": [ { "@id": "http://www.loc.gov/premis/rdf/v3/Copyright" }, { "@id": "http://www.loc.gov/premis/rdf/v3/License" }, { "@id": "http://www.loc.gov/premis/rdf/v3/InstitutionalPolicy" } ], "http://www.w3.org/2000/01/rdf-schema#isDefinedBy": [ { "@id": "http://www.loc.gov/premis/rdf/v3/" } ] },  { "@id": "http://www.loc.gov/premis/rdf/v3/compositionLevel", "@type": [ "http://www.w3.org/2002/07/owl#DatatypeProperty" ], "http://www.w3.org/2000/01/rdf-schema#label": [ { "@language": "en",
"@value": "has composition level" } ], "http://www.w3.org/2000/01/rdf-schema#domain": [ { "@id": "http://www.loc.gov/premis/rdf/v3/File" } ], "http://www.w3.org/2000/01/rdf-schema#range": [ { "@id": "http://www.w3.org/2001/XMLSchema#nonNegativeInteger" } ], "http://www.w3.org/2000/01/rdf-schema#isDefinedBy": [ { "@id": "http://www.loc.gov/premis/rdf/v3/" } ] },  { "@id": "http://www.loc.gov/premis/rdf/v3/Identifier", "@type": [ "http://www.w3.org/2002/07/owl#Class" ], "http://www.w3.org/2000/01/rdf-schema#label": [ { "@language": "en",
"@value": "Identifier" } ], "http://www.w3.org/2000/01/rdf-schema#comment": [ { "@language": "en",
"@value": "An unambiguous reference to the PREMIS entity within the preservation\r\n      repository." } ], "http://www.w3.org/2000/01/rdf-schema#isDefinedBy": [ { "@id": "http://www.loc.gov/premis/rdf/v3/" } ] },  { "@id": "http://www.loc.gov/premis/rdf/v3/purpose", "@type": [ "http://www.w3.org/2002/07/owl#ObjectProperty" ], "http://www.w3.org/2000/01/rdf-schema#label": [ { "@language": "en",
"@value": "has purpose" } ], "http://www.w3.org/2000/01/rdf-schema#domain": [ { "@id": "http://www.loc.gov/premis/rdf/v3/Dependency" } ], "http://www.w3.org/2000/01/rdf-schema#range": [ { "@id": "http://www.loc.gov/premis/rdf/v3/Action" } ], "http://www.w3.org/2000/01/rdf-schema#isDefinedBy": [ { "@id": "http://www.loc.gov/premis/rdf/v3/" } ] },  { "@id": "http://www.loc.gov/premis/rdf/v3/relationship", "@type": [ "http://www.w3.org/2002/07/owl#ObjectProperty" ], "http://www.w3.org/2000/01/rdf-schema#label": [ { "@language": "en",
"@value": "has relationship" } ], "http://www.w3.org/2000/01/rdf-schema#domain": [ { "@id": "_:b700wwwdOtlocdOtgovpremisrdfv3relationship" } ], "http://www.w3.org/2000/01/rdf-schema#range": [ { "@id": "http://www.loc.gov/premis/rdf/v3/Object" } ], "http://www.w3.org/2000/01/rdf-schema#isDefinedBy": [ { "@id": "http://www.loc.gov/premis/rdf/v3/" } ], "http://www.w3.org/2000/01/rdf-schema#seeAlso": [ { "@id": "http://id.loc.gov/vocabulary/preservation/relationshipSubType" } ] },  { "@id": "_:b834wwwdOtlocdOtgovpremisrdfv3endDate", "@type": [ "http://www.w3.org/2002/07/owl#Class" ], "http://www.w3.org/2002/07/owl#unionOf": [ { "@list": [{"@id": "http://www.loc.gov/premis/rdf/v3/RightsStatus"}, {"@id": "http://www.loc.gov/premis/rdf/v3/Rule"} ] } ] },  { "@id": "http://www.loc.gov/premis/rdf/v3/key", "@type": [ "http://www.w3.org/2002/07/owl#DatatypeProperty" ], "http://www.w3.org/2000/01/rdf-schema#label": [ { "@language": "en",
"@value": "has key" } ], "http://www.w3.org/2000/01/rdf-schema#domain": [ { "@id": "_:b895wwwdOtlocdOtgovpremisrdfv3key" } ], "http://www.w3.org/2000/01/rdf-schema#range": [ { "@id": "http://www.w3.org/2000/01/rdf-schema#Literal" } ], "http://www.w3.org/2000/01/rdf-schema#isDefinedBy": [ { "@id": "http://www.loc.gov/premis/rdf/v3/" } ] },  { "@id": "_:b700wwwdOtlocdOtgovpremisrdfv3relationship", "@type": [ "http://www.w3.org/2002/07/owl#Class" ], "http://www.w3.org/2002/07/owl#unionOf": [ { "@list": [{"@id": "http://www.loc.gov/premis/rdf/v3/Agent"}, {"@id": "http://www.loc.gov/premis/rdf/v3/Object"} ] } ] },  { "@id": "http://www.loc.gov/premis/rdf/v3/RightsStatus", "@type": [ "http://www.w3.org/2002/07/owl#Class", "http://www.w3.org/2002/07/owl#Class", "http://www.w3.org/2002/07/owl#Class" ], "http://www.w3.org/2000/01/rdf-schema#label": [ { "@language": "en",
"@value": "Rights status" } ], "http://www.w3.org/2000/01/rdf-schema#comment": [ { "@language": "en",
"@value": "Information about how a RightsBasis applies to a particular object." } ], "http://www.w3.org/2000/01/rdf-schema#isDefinedBy": [ { "@id": "http://www.loc.gov/premis/rdf/v3/" } ] },  { "@id": "http://www.loc.gov/premis/rdf/v3/outcome", "@type": [ "http://www.w3.org/2002/07/owl#ObjectProperty" ], "http://www.w3.org/2000/01/rdf-schema#label": [ { "@language": "en",
"@value": "has outcome" } ], "http://www.w3.org/2000/01/rdf-schema#domain": [ { "@id": "http://www.loc.gov/premis/rdf/v3/Event" } ], "http://www.w3.org/2000/01/rdf-schema#range": [ { "@id": "http://www.loc.gov/premis/rdf/v3/OutcomeStatus" } ], "http://www.w3.org/2000/01/rdf-schema#isDefinedBy": [ { "@id": "http://www.loc.gov/premis/rdf/v3/" } ] },  { "@id": "http://www.loc.gov/premis/rdf/v3/SignificantProperties", "@type": [ "http://www.w3.org/2002/07/owl#Class" ], "http://www.w3.org/2000/01/rdf-schema#label": [ { "@language": "en",
"@value": "Significant properties" } ], "http://www.w3.org/2000/01/rdf-schema#comment": [ { "@language": "en",
"@value": "Characteristics of a particular object subjectively determined to be important to maintain\r\n      through preservation actions." } ], "http://www.w3.org/2000/01/rdf-schema#subClassOf": [ { "@id": "http://www.loc.gov/premis/rdf/v3/PreservationPolicy" } ], "http://www.w3.org/2000/01/rdf-schema#isDefinedBy": [ { "@id": "http://www.loc.gov/premis/rdf/v3/" } ] },  { "@id": "http://www.loc.gov/premis/rdf/v3/medium", "@type": [ "http://www.w3.org/2002/07/owl#ObjectProperty" ], "http://www.w3.org/2000/01/rdf-schema#label": [ { "@language": "en",
"@value": "has medium" } ], "http://www.w3.org/2000/01/rdf-schema#domain": [ { "@id": "http://www.loc.gov/premis/rdf/v3/StorageLocation" } ], "http://www.w3.org/2000/01/rdf-schema#range": [ { "@id": "http://www.loc.gov/premis/rdf/v3/StorageMedium" } ], "http://www.w3.org/2000/01/rdf-schema#isDefinedBy": [ { "@id": "http://www.loc.gov/premis/rdf/v3/" } ] },  { "@id": "http://www.loc.gov/premis/rdf/v3/version", "@type": [ "http://www.w3.org/2002/07/owl#DatatypeProperty" ], "http://www.w3.org/2000/01/rdf-schema#label": [ { "@language": "en",
"@value": "has version" } ], "http://www.w3.org/2000/01/rdf-schema#domain": [ { "@id": "_:b1046wwwdOtlocdOtgovpremisrdfv3version" } ], "http://www.w3.org/2000/01/rdf-schema#range": [ { "@id": "http://www.w3.org/2000/01/rdf-schema#Literal" } ], "http://www.w3.org/2000/01/rdf-schema#isDefinedBy": [ { "@id": "http://www.loc.gov/premis/rdf/v3/" } ] },  { "@id": "http://www.loc.gov/premis/rdf/v3/EnvironmentCharacteristic", "@type": [ "http://www.w3.org/2002/07/owl#Class" ], "http://www.w3.org/2000/01/rdf-schema#label": [ { "@language": "en",
"@value": "Environment characteristic" } ], "http://www.w3.org/2000/01/rdf-schema#comment": [ { "@language": "en",
"@value": "An assessment of the extent to which the described environment supports its\r\n      purpose." } ], "http://www.w3.org/2000/01/rdf-schema#isDefinedBy": [ { "@id": "http://www.loc.gov/premis/rdf/v3/" } ], "http://www.w3.org/2000/01/rdf-schema#seeAlso": [ { "@id": "http://id.loc.gov/vocabulary/preservation/environmentCharacteristic" } ] } ]